{
  "main": {
    "id": "e4df4972aaacb2cf",
    "type": "split",
    "children": [
      {
        "id": "5aca6da8d5e18911",
        "type": "tabs",
        "children": [
          {
            "id": "6fc2bcf3801c2290",
            "type": "leaf",
            "pinned": true,
            "state": {
              "type": "graph",
              "state": {},
              "pinned": true,
              "icon": "lucide-git-fork",
              "title": "Visualização em gráfico"
            }
          },
          {
            "id": "c73062ca258cccac",
            "type": "leaf",
            "state": {
              "type": "markdown",
              "state": {
                "file": "AWS-Data-Engineer-Certificacao/Migration-And-Transfer/AWS Transfer Family.md",
                "mode": "source",
                "source": false
              },
              "icon": "lucide-file",
              "title": "AWS Transfer Family"
            }
          },
          {
            "id": "01d35333f48444c8",
            "type": "leaf",
            "state": {
              "type": "markdown",
              "state": {
                "file": "AWS-Data-Engineer-Certificacao/Database/Amazon DynamoDB.md",
                "mode": "source",
                "source": false
              },
              "icon": "lucide-file",
              "title": "Amazon DynamoDB"
            }
          }
        ],
        "currentTab": 1
      }
    ],
    "direction": "vertical"
  },
  "left": {
    "id": "64f59dd24ff443a4",
    "type": "split",
    "children": [
      {
        "id": "2bd1d66c4216b0fe",
        "type": "tabs",
        "children": [
          {
            "id": "3ed7aed7b0651bcb",
            "type": "leaf",
            "state": {
              "type": "file-explorer",
              "state": {
                "sortOrder": "alphabetical",
                "autoReveal": false
              },
              "icon": "lucide-folder-closed",
              "title": "Explorador de arquivos"
            }
          },
          {
            "id": "ca7a26f96edc0fda",
            "type": "leaf",
            "state": {
              "type": "search",
              "state": {
                "query": "",
                "matchingCase": false,
                "explainSearch": false,
                "collapseAll": false,
                "extraContext": false,
                "sortOrder": "alphabetical"
              },
              "icon": "lucide-search",
              "title": "Procurar"
            }
          },
          {
            "id": "7f4b9c727b41691d",
            "type": "leaf",
            "state": {
              "type": "bookmarks",
              "state": {},
              "icon": "lucide-bookmark",
              "title": "Marcadores"
            }
          }
        ]
      }
    ],
    "direction": "horizontal",
    "width": 369.5
  },
  "right": {
    "id": "82984997119a3f03",
    "type": "split",
    "children": [
      {
        "id": "10739f157fce5232",
        "type": "tabs",
        "children": [
          {
            "id": "eb07064cf4523bb6",
            "type": "leaf",
            "state": {
              "type": "backlink",
              "state": {
                "collapseAll": false,
                "extraContext": false,
                "sortOrder": "alphabetical",
                "showSearch": false,
                "searchQuery": "",
                "backlinkCollapsed": false,
                "unlinkedCollapsed": true
              },
              "icon": "links-coming-in",
              "title": "Backlinks"
            }
          },
          {
            "id": "67690a711eeb5f9b",
            "type": "leaf",
            "state": {
              "type": "outgoing-link",
              "state": {
                "file": "AWS-Data-Engineer-Certificacao/Storage/Amazon Simple Storage Service (Amazon S3).md",
                "linksCollapsed": true,
                "unlinkedCollapsed": true
              },
              "icon": "links-going-out",
              "title": "Links de saída para Amazon Simple Storage Service (Amazon S3)"
            }
          },
          {
            "id": "341fad5b73d330f1",
            "type": "leaf",
            "state": {
              "type": "tag",
              "state": {
                "sortOrder": "frequency",
                "useHierarchy": true,
                "showSearch": false,
                "searchQuery": ""
              },
              "icon": "lucide-tags",
              "title": "Tags"
            }
          },
          {
            "id": "0c6f146f465b1204",
            "type": "leaf",
            "state": {
              "type": "outline",
              "state": {
                "file": "AWS-Data-Engineer-Certificacao/Storage/Amazon Simple Storage Service (Amazon S3).md",
                "followCursor": false,
                "showSearch": false,
                "searchQuery": ""
              },
              "icon": "lucide-list",
              "title": "Sumário de Amazon Simple Storage Service (Amazon S3)"
            }
          },
          {
            "id": "ed252064a4241bc3",
            "type": "leaf",
            "state": {
              "type": "git-view",
              "state": {},
              "icon": "git-pull-request",
              "title": "Source Control"
            }
          }
        ],
        "currentTab": 4
      }
    ],
    "direction": "horizontal",
    "width": 300
  },
  "left-ribbon": {
    "hiddenItems": {
      "bases:Criar nova base": false,
      "switcher:Abrir a troca rápida": false,
      "graph:Abrir visualização em gráfico": false,
      "canvas:Criar novo canvas": false,
      "daily-notes:Abrir a nota de hoje": false,
      "templates:Inserir modelo": false,
      "command-palette:Abrir paleta de comandos": false,
      "obsidian-git:Open Git source control": false
    }
  },
  "active": "c73062ca258cccac",
  "lastOpenFiles": [
    "Pasted image 20250922173732.png",
    "AWS-Data-Engineer-Certificacao/Migration-And-Transfer/AWS Snow Family.md",
    "AWS-Data-Engineer-Certificacao/Migration-And-Transfer/AWS DataSync.md",
    "Pasted image 20250922173449.png",
    "Pasted image 20250922173436.png",
    "AWS-Data-Engineer-Certificacao/Migration-And-Transfer/AWS Database Migration Service (AWS DMS).md",
    "Pasted image 20250922173400.png",
    "AWS-Data-Engineer-Certificacao/Database/Amazon DynamoDB.md",
    "Pasted image 20250922173243.png",
    "Pasted image 20250922173226.png",
    "Pasted image 20250922173153.png",
    "AWS-Data-Engineer-Certificacao/Migration-And-Transfer/AWS Application Discovery Service e Migration Service.md",
    "AWS-Data-Engineer-Certificacao/Migration-And-Transfer/AWS Application Migration Service.md",
    "Pasted image 20250922172938.png",
    "AWS-Data-Engineer-Certificacao/Database/Amazon DocumentDB (with MongoDB compatibility).md",
    "AWS-Data-Engineer-Certificacao/Database/Amazon RedShift.md",
    "Pasted image 20250920115442.png",
    "Pasted image 20250920113318.png",
    "AWS-Data-Engineer-Certificacao/Data-Engineering-Fundamentals/Data Sources.md",
    "AWS-Data-Engineer-Certificacao/Data-Engineering-Fundamentals/OLAP VS OLTP.md",
    "AWS-Data-Engineer-Certificacao/Data-Engineering-Fundamentals/ETL e ELT.md",
    "Pasted image 20250920110413.png",
    "AWS-Data-Engineer-Certificacao/Compute/Amazon Elastic Compute Cloud (Amazon EC2).md",
    "Sem título 1.base",
    "Sem título.base",
    "AWS-Data-Engineer-Certificacao/Database/Amazon Timestream.md",
    "AWS-Data-Engineer-Certificacao/Database/Amazon Neptune.md",
    "AWS-Data-Engineer-Certificacao/Database/Amazon Keyspaces (for Apache Cassandra).md",
    "AWS-Data-Engineer-Certificacao/Database/Amazon MemoryDB for Redis.md",
    "AWS-Data-Engineer-Certificacao/Database/Amazon Relational Database Service (Amazon RDS).md",
    "AWS-Data-Engineer-Certificacao/Database/RDS.md",
    "AWS-Data-Engineer-Certificacao/Temas/App Integration.md",
    "AWS-Data-Engineer-Certificacao/Compute/AWS Elastic Load Balance.md",
    "AWS-Data-Engineer-Certificacao/Compute/AWS Lambda.md",
    "AWS-Data-Engineer-Certificacao/Compute/AWS Serverless Application Repository.md",
    "AWS-Data-Engineer-Certificacao/Compute/Escalabilidade e alta disponibilidade.md",
    "AWS-Data-Engineer-Certificacao/Compute/AWS Batch.md",
    "AWS-Data-Engineer-Certificacao/Containers/Amazon Elastic Container Registry (Amazon ECR).md",
    "AWS-Data-Engineer-Certificacao/Temas/Sem título",
    "AWS-Data-Engineer-Certificacao/Data-Engineering-Fundamentals",
    "Security-Identity-And-Compliance",
    "AWS-Data-Engineer-Certificacao/Temas",
    "Sem título.canvas",
    "create_path.py",
    "AWS-Data-Engineer/AWS-Data-Engineer-Certificacao/Migration-And-Transfer",
    "AWS-Data-Engineer/AWS-Data-Engineer-Certificacao/Storage",
    "AWS-Data-Engineer/AWS-Data-Engineer-Certificacao/Security,-Identity,-And-Compliance"
  ]
}